README.rst
setup.py
varsity.py
varsity.egg-info/PKG-INFO
varsity.egg-info/SOURCES.txt
varsity.egg-info/dependency_links.txt
varsity.egg-info/not-zip-safe
varsity.egg-info/requires.txt
varsity.egg-info/top_level.txt