Metadata-Version: 1.1
Name: varsity
Version: 0.0.5
Summary: A library for defining, parsing, and validating settings passed as environment variables
Home-page: http://github.com/btubbs/varsity
Author: Brent Tubbs
Author-email: brent.tubbs@gmail.com
License: BSD
Platform: UNKNOWN
Classifier: Development Status :: 4 - Beta
Classifier: Intended Audience :: Developers
Classifier: License :: OSI Approved :: BSD License
Classifier: Operating System :: OS Independent
Classifier: Programming Language :: Python
Classifier: Programming Language :: Python :: 2
Classifier: Programming Language :: Python :: 2.7
Classifier: Programming Language :: Python :: 3
Classifier: Programming Language :: Python :: 3.5
